<HR8799><c><s100715_a010001_tlc_Kbb_020.fits sep="0.95" stardir="left" xADIcen="-32.40914067" xdefcen="-37.79802955665025" xvisucen="-35.79802955665025" yADIcen="32.94444444" ydefcen="32" yvisucen="32" /><s100715_a011001_tlc_Kbb_020.fits sep="0.95" stardir="left" xADIcen="-32.85358511" xdefcen="-37.79802955665025" xvisucen="-34.79802955665025" yADIcen="31.05555556" ydefcen="32" yvisucen="27" /><s100715_a012001_tlc_Kbb_020.fits sep="0.95" stardir="left" xADIcen="-32.63136289" xdefcen="-37.79802955665025" xvisucen="-34.79802955665025" yADIcen="37.38888889" ydefcen="32" yvisucen="33" /><s100715_a013001_tlc_Kbb_020.fits sep="0.95" stardir="left" xADIcen="-32.96469622" xdefcen="-37.79802955665025" xvisucen="-34.79802955665025" yADIcen="41.38888889" ydefcen="32" yvisucen="39" /><s100715_a014001_tlc_Kbb_020.fits sep="0.95" stardir="left" xADIcen="-40.63136289" xdefcen="-37.79802955665025" xvisucen="-36.79802955665025" yADIcen="38.27777778" ydefcen="32" yvisucen="33" /><s100715_a015001_tlc_Kbb_020.fits sep="0.95" stardir="left" xADIcen="-41.07580733" xdefcen="-37.79802955665025" xvisucen="-37.79802955665025" yADIcen="32.05555556" ydefcen="32" yvisucen="28" /><s100715_a016001_tlc_Kbb_020.fits sep="0.95" stardir="left" xADIcen="-40.96469622" xdefcen="-37.79802955665025" xvisucen="-38.79802955665025" yADIcen="41.83333333" ydefcen="32" yvisucen="38" /><s100715_a017001_tlc_Kbb_020.fits sep="0.95" stardir="left" xADIcen="-37.63136289" xdefcen="-37.79802955665025" xvisucen="-36.79802955665025" yADIcen="33.16666667" ydefcen="32" yvisucen="32.5" /><s100715_a018001_tlc_Kbb_020.fits sep="0.95" stardir="left" xADIcen="-40.40914067" xdefcen="-37.79802955665025" xvisucen="-37.79802955665025" yADIcen="35.27777778" ydefcen="32" yvisucen="32" /><s100715_a019001_tlc_Kbb_020.fits sep="0.95" stardir="left" xADIcen="-37.40914067" xdefcen="-37.79802955665025" xvisucen="-36.79802955665025" yADIcen="35.05555556" ydefcen="32" yvisucen="33" /><s100715_a020001_tlc_Kbb_020.fits sep="0.95" stardir="left" xADIcen="-38.85358511" xdefcen="-37.79802955665025" xvisucen="-36.79802955665025" yADIcen="37.61111111" ydefcen="32" yvisucen="35" /><s100715_a021001_tlc_Kbb_020.fits sep="0.95" stardir="left" xADIcen="0.70197044" xdefcen="-37.79802955665025" xvisucen="-36.79802955665025" yADIcen="29.05555556" ydefcen="32" yvisucen="33" /><s100715_a025001_tlc_Kbb_020.fits sep="0.95" stardir="down" xADIcen="5.72222222" xdefcen="9" xvisucen="7" yADIcen="16.29802956" ydefcen="78.79802955665025" yvisucen="80.79802955665025" /><s100715_a026001_tlc_Kbb_020.fits sep="0.95" stardir="down" xADIcen="71.5" xdefcen="9" xvisucen="5" yADIcen="16.29802956" ydefcen="78.79802955665025" yvisucen="81.79802955665025" /><s100715_a027001_tlc_Kbb_020.fits sep="0.95" stardir="down" xADIcen="-53.5" xdefcen="9" xvisucen="8" yADIcen="16.29802956" ydefcen="78.79802955665025" yvisucen="81.79802955665025" /><s100715_a028001_tlc_Kbb_020.fits sep="0.95" stardir="down" xADIcen="-53.5" xdefcen="9" xvisucen="7.5" yADIcen="16.29802956" ydefcen="78.79802955665025" yvisucen="79.79802955665025" /><s100715_a029001_tlc_Kbb_020.fits sep="0.95" stardir="down" xADIcen="-53.5" xdefcen="9" xvisucen="9.5" yADIcen="16.29802956" ydefcen="78.79802955665025" yvisucen="81.29802955665025" /><s101104_a014001_tlc_Kbb_020.fits sep="0.95" stardir="left" xADIcen="6.03530378" xdefcen="-37.79802955665025" xvisucen="-37.79802955665025" yADIcen="8.05555556" ydefcen="32" yvisucen="32" /><s101104_a016001_tlc_Kbb_020.fits sep="0.95" stardir="left" xADIcen="12.257526" xdefcen="-37.79802955665025" xvisucen="-37.79802955665025" yADIcen="31.72222222" ydefcen="32" yvisucen="32" /><s101104_a026001_tlc_Kbb_020.fits sep="0.95" stardir="left" xADIcen="-38.63136289" xdefcen="-37.79802955665025" xvisucen="-37.79802955665025" yADIcen="36.61111111" ydefcen="32" yvisucen="31" /><s101104_a034001_tlc_Kbb_020.fits sep="0.95" stardir="left" xADIcen="-42.07580733" xdefcen="-37.79802955665025" xvisucen="-37.79802955665025" yADIcen="32.94444444" ydefcen="32" yvisucen="32" /><s101104_a035001_tlc_Kbb_020.fits sep="0.95" stardir="left" xADIcen="-40.52025178" xdefcen="-37.79802955665025" xvisucen="-37.79802955665025" yADIcen="33.16666667" ydefcen="32" yvisucen="32" /><s101104_a036001_tlc_Kbb_020.fits sep="0.95" stardir="left" xADIcen="-39.85358511" xdefcen="-37.79802955665025" xvisucen="-37.79802955665025" yADIcen="32.05555556" ydefcen="32" yvisucen="32" /><s101104_a037001_tlc_Kbb_020.fits sep="0.95" stardir="left" xADIcen="0.03530378" xdefcen="-37.79802955665025" xvisucen="-37.79802955665025" yADIcen="30.38888889" ydefcen="32" yvisucen="32" /><s101104_a038001_tlc_Kbb_020.fits sep="0.95" stardir="left" xADIcen="-42.07580733" xdefcen="-37.79802955665025" xvisucen="-37.79802955665025" yADIcen="30.27777778" ydefcen="32" yvisucen="32" /><s110723_a017001_tlc_Kbb_020.fits sep="0.95" stardir="left" xADIcen="24.70197044" xdefcen="-37.79802955665025" xvisucen="-37.79802955665025" yADIcen="28.16666667" ydefcen="32" yvisucen="28" /><s110723_a018001_tlc_Kbb_020.fits sep="0.95" stardir="left" xADIcen="0.92419267" xdefcen="-37.79802955665025" xvisucen="-37.79802955665025" yADIcen="37.72222222" ydefcen="32" yvisucen="22" /><s110723_a024001_tlc_Kbb_020.fits sep="0.95" stardir="left" xADIcen="0.14641489" xdefcen="-37.79802955665025" xvisucen="-37.79802955665025" yADIcen="36.72222222" ydefcen="32" yvisucen="32" /><s110723_a025001_tlc_Kbb_020.fits sep="0.95" stardir="left" xADIcen="3.53037767e-02" xdefcen="-37.79802955665025" xvisucen="-37.79802955665025" yADIcen="3.77222222e+01" ydefcen="32" yvisucen="28" /><s110723_a026001_tlc_Kbb_020.fits sep="0.95" stardir="left" xADIcen="3.53037767e-02" xdefcen="-37.79802955665025" xvisucen="-37.79802955665025" yADIcen="3.68333333e+01" ydefcen="32" yvisucen="28" /><s110723_a027001_tlc_Kbb_020.fits sep="0.95" stardir="left" xADIcen="-0.07580733" xdefcen="-37.79802955665025" xvisucen="-37.79802955665025" yADIcen="38.16666667" ydefcen="32" yvisucen="24" /><s110723_a032001_tlc_Kbb_020.fits sep="0.95" stardir="left" xADIcen="-0.07580733" xdefcen="-37.79802955665025" xvisucen="-37.79802955665025" yADIcen="33.05555556" ydefcen="32" yvisucen="29" /><s110723_a033001_tlc_Kbb_020.fits sep="0.95" stardir="left" xADIcen="2.03530378" xdefcen="-37.79802955665025" xvisucen="-38.79802955665025" yADIcen="-30.5" ydefcen="32" yvisucen="40" /><s110723_a034001_tlc_Kbb_020.fits sep="0.95" stardir="left" xADIcen="-0.07580733" xdefcen="-37.79802955665025" xvisucen="-38.79802955665025" yADIcen="55.72222222" ydefcen="32" yvisucen="21" /><s110724_a030001_tlc_Kbb_020.fits sep="0.95" stardir="left" xADIcen="-47.742474" xdefcen="-37.79802955665025" xvisucen="-37.79802955665025" yADIcen="21.94444444" ydefcen="32" yvisucen="32" /><s110724_a032001_tlc_Kbb_020.fits sep="0.95" stardir="left" xADIcen="0.92419267" xdefcen="-37.79802955665025" xvisucen="-37.79802955665025" yADIcen="34.5" ydefcen="32" yvisucen="31" /><s110724_a038001_tlc_Kbb_020.fits sep="0.95" stardir="left" xADIcen="2.47974822" xdefcen="-37.79802955665025" xvisucen="-37.79802955665025" yADIcen="32.05555556" ydefcen="32" yvisucen="31" /></c></HR8799>